flake8_init_return.py
flake8_init_return-1.0.1.dist-info/LICENSE
flake8_init_return-1.0.1.dist-info/METADATA
flake8_init_return-1.0.1.dist-info/WHEEL
flake8_init_return-1.0.1.dist-info/entry_points.txt
flake8_init_return-1.0.1.dist-info/top_level.txt
flake8_init_return-1.0.1.dist-info/RECORD
