Metadata-Version: 2.1
Name: flake8_init_return
Version: 1.0.1
Summary: flake8 plugin which makes sure that __init__ functions have a return type
Home-page: https://github.com/keller00/flake8-init-return
Author: Mark Keller
Author-email: mark@markkeller.dev
License: MIT
Classifier: License :: OSI Approved :: MIT License
Classifier: Programming Language :: Python :: 3
Classifier: Programming Language :: Python :: 3 :: Only
Classifier: Programming Language :: Python :: Implementation :: CPython
Requires-Python: >=3.8
License-File: LICENSE
Requires-Dist: flake8 >=3.7
